odoo/addons/__init__.py
odoo/addons/hr_recruitment/README.md
odoo/addons/hr_recruitment/__init__.py
odoo/addons/hr_recruitment/__manifest__.py
odoo/addons/hr_recruitment/data/hr_recruitment_data.xml
odoo/addons/hr_recruitment/data/hr_recruitment_demo.xml
odoo/addons/hr_recruitment/data/hr_recruitment_demo_jones_cv.pdf
odoo/addons/hr_recruitment/data/hr_recruitment_demo_jose_cv.txt
odoo/addons/hr_recruitment/data/hr_recruitment_demo_williams_cv.doc
odoo/addons/hr_recruitment/i18n/af.po
odoo/addons/hr_recruitment/i18n/am.po
odoo/addons/hr_recruitment/i18n/ar.po
odoo/addons/hr_recruitment/i18n/bg.po
odoo/addons/hr_recruitment/i18n/bs.po
odoo/addons/hr_recruitment/i18n/ca.po
odoo/addons/hr_recruitment/i18n/cs.po
odoo/addons/hr_recruitment/i18n/da.po
odoo/addons/hr_recruitment/i18n/de.po
odoo/addons/hr_recruitment/i18n/el.po
odoo/addons/hr_recruitment/i18n/en_GB.po
odoo/addons/hr_recruitment/i18n/es.po
odoo/addons/hr_recruitment/i18n/es_BO.po
odoo/addons/hr_recruitment/i18n/es_CL.po
odoo/addons/hr_recruitment/i18n/es_CO.po
odoo/addons/hr_recruitment/i18n/es_CR.po
odoo/addons/hr_recruitment/i18n/es_DO.po
odoo/addons/hr_recruitment/i18n/es_EC.po
odoo/addons/hr_recruitment/i18n/es_PE.po
odoo/addons/hr_recruitment/i18n/es_PY.po
odoo/addons/hr_recruitment/i18n/es_VE.po
odoo/addons/hr_recruitment/i18n/et.po
odoo/addons/hr_recruitment/i18n/eu.po
odoo/addons/hr_recruitment/i18n/fa.po
odoo/addons/hr_recruitment/i18n/fi.po
odoo/addons/hr_recruitment/i18n/fo.po
odoo/addons/hr_recruitment/i18n/fr.po
odoo/addons/hr_recruitment/i18n/fr_BE.po
odoo/addons/hr_recruitment/i18n/fr_CA.po
odoo/addons/hr_recruitment/i18n/gl.po
odoo/addons/hr_recruitment/i18n/gu.po
odoo/addons/hr_recruitment/i18n/he.po
odoo/addons/hr_recruitment/i18n/hi.po
odoo/addons/hr_recruitment/i18n/hr.po
odoo/addons/hr_recruitment/i18n/hu.po
odoo/addons/hr_recruitment/i18n/id.po
odoo/addons/hr_recruitment/i18n/is.po
odoo/addons/hr_recruitment/i18n/it.po
odoo/addons/hr_recruitment/i18n/ja.po
odooku_odoo_hr_recruitment-11.0.7.dist-info/LICENSE
odooku_odoo_hr_recruitment-11.0.7.dist-info/METADATA
odooku_odoo_hr_recruitment-11.0.7.dist-info/WHEEL
odooku_odoo_hr_recruitment-11.0.7.dist-info/top_level.txt
odooku_odoo_hr_recruitment-11.0.7.dist-info/RECORD
